eve_scripts/update_hmm_job.sh
mitos/CONFIG.py
mitos/CONFIG.py.sample
mitos/__init__.py
mitos/_version.py
mitos/booreparser.py
mitos/cmsearch_parse_separate.py
mitos/codoncount.py
mitos/convert_tree.py
mitos/create_prot_fasta.py
mitos/get-wancy.py
mitos/inihit.py
mitos/merge_results.py
mitos/mitoch_revisions.py
mitos/mitoloc.py
mitos/mitos-extension.py
mitos/mitos-extension2.py
mitos/mumcmp.py
mitos/names.py
mitos/ogre-geneorder.py
mitos/plot_evalues.R
mitos/plot_gapfractions.R
mitos/plotprot.R
mitos/plotrna.R
mitos/plotstst.R
mitos/prepareFiles.py
mitos/removegene.py
mitos/skew.py
mitos/trna-cm.py
mitos/trnadist.py
mitos/trnascan_parse_separate.py
mitos/update-mitolog.py
mitos/bedfile/__init__.py
mitos/blast/__init__.py
mitos/draw/__init__.py
mitos/extprog/__init__.py
mitos/feature/__init__.py
mitos/gb/__init__.py
mitos/gb/unify.py
mitos/gfffile/__init__.py
mitos/mergefeature/__init__.py
mitos/mitfi/__init__.py
mitos/mitfi/parser/improve_infernal_structure.jar
mitos/mitfi/parser/mitfiGeneticCodes
mitos/mitfi/parser/mitfi_import-1.1.jar
mitos/mitfi/parser/mitfi_import-1.1.jar.old
mitos/mitfi/parser/mitfi_import-1.1.jar.org
mitos/mitfi/parser/mitfi_import-1.1.jar.org.pre-circ
mitos/mitfi/parser/mitfi_import.jar
mitos/mito/__init__.py
mitos/mitofile/__init__.py
mitos/protfeat/__init__.py
mitos/rna/__init__.py
mitos/rna/forester.py
mitos/rna/vienna.py
mitos/scripts/__init__.py
mitos/scripts/analyse.py
mitos/scripts/drawmitos.py
mitos/scripts/gcpp.py
mitos/scripts/getfeatures.py
mitos/scripts/getinfo.py
mitos/scripts/refseqsplit.py
mitos/scripts/runmitos.py
mitos/scripts/subseq.py
mitos/scripts/taxtree.py
mitos/scripts/update_blastdb.py
mitos/scripts/update_hmm.py
mitos/sequence/__init__.py
mitos/sequence/degenerate.py
mitos/tax/__init__.py
mitos/tbl/__init__.py
mitos/trna/__init__.py
mitos/trna/arwenscan.py
mitos/trna/trnascan.py
mitos/update/__init__.py
mitos/util/__init__.py
mitos-2.1.10.data/scripts/plotprot.R
mitos-2.1.10.data/scripts/plotrna.R
mitos-2.1.10.dist-info/LICENSE
mitos-2.1.10.dist-info/METADATA
mitos-2.1.10.dist-info/WHEEL
mitos-2.1.10.dist-info/entry_points.txt
mitos-2.1.10.dist-info/top_level.txt
mitos-2.1.10.dist-info/RECORD
