Metadata-Version: 2.1
Name: mitos
Version: 2.1.10
Summary: MITOS: de novo annotation of metazoan mitochondrial genomes
Author-email: Matthias Bernt <m.bernt@ufz.de>
License: MIT
Project-URL: Homepage, http://mitos.bioinf.uni-leipzig.de
Project-URL: Download, https://gitlab.com/Bernt/MITOS
Project-URL: Repository, https://gitlab.com/Bernt/MITOS
Classifier: Environment :: Console
Classifier: Intended Audience :: Science/Research
Classifier: Programming Language :: Python :: 3
Classifier: Operating System :: OS Independent
Classifier: Topic :: Scientific/Engineering :: Bio-Informatics
Requires-Python: <3.8,>=3.7
License-File: LICENSE
Requires-Dist: biopython ==1.73
Provides-Extra: dev
Requires-Dist: flake8 ==5.0.4 ; extra == 'dev'
Requires-Dist: black ==22.10.0 ; extra == 'dev'
Requires-Dist: isort ==5.11.5 ; extra == 'dev'
Requires-Dist: mypy ==1.4.1 ; extra == 'dev'
Requires-Dist: pytest ==7.4.4 ; extra == 'dev'
Requires-Dist: tox ==3.28.0 ; extra == 'dev'
Requires-Dist: twine ==4.0.2 ; extra == 'dev'
